polygone_nms/__init__.py
polygone_nms/nms.py
polygone_nms/utils.py
polygone_nms-0.1.7.dist-info/LICENSE
polygone_nms-0.1.7.dist-info/METADATA
polygone_nms-0.1.7.dist-info/WHEEL
polygone_nms-0.1.7.dist-info/top_level.txt
polygone_nms-0.1.7.dist-info/RECORD
