Metadata-Version: 2.1
Name: polygone-nms
Version: 0.1.7
Summary: Efficient and distributed polygon Non-Maximum Suppression (NMS) library
Home-page: https://github.com/WolodjaZ/polygone-nms
Author: Vladimir Zaigrajew
Author-email: vladimirzaigrajew@gmail.com
Classifier: Programming Language :: Python :: 3.8
Classifier: Programming Language :: Python :: 3.9
Classifier: Programming Language :: Python :: 3.10
Classifier: Development Status :: 3 - Alpha
Classifier: Intended Audience :: Developers
Classifier: License :: OSI Approved :: MIT License
Classifier: Operating System :: OS Independent
Classifier: Topic :: Scientific/Engineering :: Image Processing
Classifier: Topic :: Scientific/Engineering :: Artificial Intelligence
Classifier: Topic :: Scientific/Engineering :: Information Analysis
Classifier: Topic :: Scientific/Engineering :: Mathematics
Classifier: Topic :: Software Development :: Libraries :: Python Modules
Classifier: Topic :: Utilities
Requires-Python: >=3.8
License-File: LICENSE
Requires-Dist: numpy (==1.24.3)
Requires-Dist: shapely (==2.0.1)
Requires-Dist: rtree (==1.0.1)
Provides-Extra: dev
Requires-Dist: pytest (==7.3.1) ; extra == 'dev'
Requires-Dist: pytest-cov (==4.0.0) ; extra == 'dev'
Requires-Dist: black (==23.3.0) ; extra == 'dev'
Requires-Dist: flake8 (==6.0.0) ; extra == 'dev'
Requires-Dist: isort (==5.12.0) ; extra == 'dev'
Requires-Dist: mypy (==1.2.0) ; extra == 'dev'
Requires-Dist: pre-commit (==3.2.2) ; extra == 'dev'
Requires-Dist: tox (==4.4.12) ; extra == 'dev'
Requires-Dist: ray (==2.3.1) ; extra == 'dev'
Requires-Dist: dask[distributed] (==2023.4.0) ; extra == 'dev'
Provides-Extra: docs
Requires-Dist: mkdocs (==1.4.2) ; extra == 'docs'
Requires-Dist: mkdocs-material (==9.1.8) ; extra == 'docs'
Requires-Dist: mkdocstrings[python] (==0.21.2) ; extra == 'docs'
Requires-Dist: mike (==1.1.2) ; extra == 'docs'
